aiofiledol/__init__.py
aiofiledol-0.0.3.dist-info/LICENSE
aiofiledol-0.0.3.dist-info/METADATA
aiofiledol-0.0.3.dist-info/WHEEL
aiofiledol-0.0.3.dist-info/top_level.txt
aiofiledol-0.0.3.dist-info/RECORD
