Metadata-Version: 2.1
Name: aiofiledol
Version: 0.0.3
Summary: aiofile (async filesys operations) with a simple (dict-like or list-like) interface
Home-page: https://github.com/i2mint/aiofiledol
Author: OtoSense
License: apache-2.0
Platform: any
Requires-Dist: dol
Requires-Dist: aiofile
